<?xml version="1.0" encoding="UTF-8"?>
<!--

    Copyright 2014 SAP AG

    Licensed under the Apache License, Version 2.0 (the "License");
    you may not use this file except in compliance with the License.
    You may obtain a copy of the License at

        http://www.apache.org/licenses/LICENSE-2.0

    Unless required by applicable law or agreed to in writing, software
    distributed under the License is distributed on an "AS IS" BASIS,
    WITHOUT WARRANTIES OR CONDITIONS OF ANY KIND, either express or implied.
    See the License for the specific language governing permissions and
    limitations under the License.

-->
<root name="Root" detectable="false"
	xmlns="http://www.sopeco.org/PerformanceProblemHierarchySchema"
	xmlns:xsi="http://www.w3.org/2001/XMLSchema-instance"
	xsi:schemaLocation="http://www.sopeco.org/PerformanceProblemHierarchySchema http://i43vm-saas.ipd.kit.edu/schema/PerformanceProblemHierarchySchema.xsd">
	
	<problem name="HighMemoryUsage" detectable="true">
		<config key="hmu.scope" value="SERVLET" />
	</problem>
	
	<!--	
	
	<problem name="RTHiccups" detectable="true">
		<config key="rth.scope" value="SERVLET" />
	</problem>
	
	<problem name="GCOverloading" detectable="true">
		<config key="gco.scope" value="SERVLET" />
	</problem>
	
	<problem name="OSJ" detectable="true">
		<config key="osj.scope" value="SERVLET" />
	</problem>
	
	<problem name="Ramp" detectable="true">
	</problem>
	
	<problem name="OLB" detectable="true">
		<config key="olb.scope" value="SERVLET" />
		<problem name="OLB" detectable="true">
			<config key="olb.scope" value="SYNCHRONIZED" />
		</problem>
	</problem> -->

</root>